README.md
setup.py
aanalyticsact_eu/__init__.py
aanalyticsact_eu/__version__.py
aanalyticsact_eu/actExecute.py
aanalyticsact_eu/actModuler.py
aanalyticsact_eu/actRunner.py
aanalyticsact_eu.egg-info/PKG-INFO
aanalyticsact_eu.egg-info/SOURCES.txt
aanalyticsact_eu.egg-info/dependency_links.txt
aanalyticsact_eu.egg-info/not-zip-safe
aanalyticsact_eu.egg-info/requires.txt
aanalyticsact_eu.egg-info/top_level.txt